LICENSE
README.md
setup.py
itea/__init__.py
itea.egg-info/PKG-INFO
itea.egg-info/SOURCES.txt
itea.egg-info/dependency_links.txt
itea.egg-info/requires.txt
itea.egg-info/top_level.txt
itea/_base/_BaseITEA.py
itea/_base/_BaseITExpr.py
itea/_base/__init__.py
itea/_manipulators/__init__.py
itea/_manipulators/generator.py
itea/_manipulators/mutation.py
itea/_manipulators/sanitizer.py
itea/_manipulators/simplifier.py
itea/classification/_ITEA_classifier.py
itea/classification/_ITExpr_classifier.py
itea/classification/__init__.py
itea/inspection/_ITEA_summarizer.py
itea/inspection/_ITExpr_explainer.py
itea/inspection/_ITExpr_inspector.py
itea/inspection/_ITExpr_texifier.py
itea/inspection/__init__.py
itea/regression/_ITEA_regressor.py
itea/regression/_ITExpr_regressor.py
itea/regression/__init__.py
tests/__init__.py
tests/test_BaseITEA.py
tests/test_BaseITExpr.py
tests/test_classifier.py
tests/test_manipulators.py
tests/test_mutations.py
tests/test_regressor.py