Metadata-Version: 2.1
Name: itea
Version: 1.0.1
Summary: Interaction-Transformation Evolutionary Algorithm for Symbolic Regression.
Home-page: UNKNOWN
Author: Guilherme Aldeia
Author-email: guilherme.aldeia@ufabc.edu.br
License: BSD-3-Clause
Platform: UNKNOWN
Requires-Python: >=3.7
License-File: LICENSE
